multi_doc_mcp/__init__.py
multi_doc_mcp/__main__.py
multi_doc_mcp/server.py
multi_doc_mcp/converters/__init__.py
multi_doc_mcp/converters/base_converter.py
multi_doc_mcp/converters/excel_to_md.py
multi_doc_mcp/converters/pdf_to_md.py
multi_doc_mcp/converters/ppt_to_md.py
multi_doc_mcp/converters/word_to_md.py
multi_doc_mcp/utils/__init__.py
multi_doc_mcp/utils/file_utils.py
multi_doc_mcp/utils/validation.py
markdown_format_converter_mcp-1.0.1.dist-info/METADATA
markdown_format_converter_mcp-1.0.1.dist-info/WHEEL
markdown_format_converter_mcp-1.0.1.dist-info/entry_points.txt
markdown_format_converter_mcp-1.0.1.dist-info/RECORD
