Metadata-Version: 2.4
Name: markdown-format-converter-mcp
Version: 1.0.1
Summary: 统一的文档格式转换MCP服务器 - 支持Excel、PDF、PPT、Word与Markdown互转
Author: MCP Team
License: MIT
Classifier: Development Status :: 4 - Beta
Classifier: Intended Audience :: Developers
Classifier: License :: OSI Approved :: MIT License
Classifier: Programming Language :: Python :: 3
Classifier: Programming Language :: Python :: 3.10
Classifier: Programming Language :: Python :: 3.11
Classifier: Programming Language :: Python :: 3.12
Requires-Python: >=3.10
Requires-Dist: markitdown[all]>=0.0.1
Requires-Dist: mcp>=1.0.0
Requires-Dist: openpyxl>=3.1.0
Requires-Dist: python-docx>=1.1.0
